{
  "all_correct": false,
  "correct_points": [
    "第18题(1)中通过中位线思路证明AC∥平面DEF，方向正确",
    "第18题(3)中参数化设点Q并列线面角方程的思路合理"
  ],
  "error_points": [
    "第17题(1)：配方后错误解不等式-m²+2m-3>0，误得m∈(-1,3)，实际r²恒负，无解",
    "第17题(2)(3)：在圆不存在的前提下继续求切线与最小值，逻辑前提失效",
    "第18题(2)：法向量点积与模长计算错误，导致cosθ与sinθ结果错误（应为√3/3而非√10/4）",
    "第18题(3)：虽思路对，但FE模长计算错误，FQ结果应为√19/4而非√3/2"
  ],
  "primary_weakness": "对问题前提条件的检验意识薄弱，尤其在解析几何中忽略‘圆存在性’等基本约束；同时向量运算中计算粗心、公式混淆（如sin/cos关系）频发",
  "knowledge_points": [
    "圆的标准方程与半径平方>0的判别条件",
    "代数配方后不等式符号与判别式分析",
    "向量叉乘、模长与夹角公式的准确计算",
    "线面角公式中sinθ = |n·v|/(|n||v|) 的正确应用",
    "解题前必须验证前提有效性（如圆是否存在、点是否在定义域内）"
  ],
  "practice_focus": [
    "每道题动笔前先问：这个图形/对象真的存在吗？",
    "强化二次函数恒正/恒负的判别训练（Δ与开口方向结合）",
    "向量运算分步验算：先写坐标→再算叉乘→再算模→最后代入公式",
    "线面角与二面角题目强制要求写出‘公式→代入→化简→结果’四步草稿"
  ],
  "user_text": "你这次主要问题不是思路不会，而是‘跳步太快’——比如第17题，配方是对的，但看到-m²+2m-3就直接因式分解，忘了它其实恒小于0；第18题向量计算时数字抄错或开方出错。最要警惕的是：数学里‘不存在’比‘算错’更致命，圆都不存在了还求切线，就像问‘独角兽的角多长’。下次做题请加一道‘前提检查’：画个√或×在题干旁，确认对象存在再往下算。向量题建议用铅笔分步写清每一步数值，避免心算失误。"
}