{
  "problem_overview": {
    "problems": [
      {
        "id": 1,
        "description": "某质点沿直线运动，位移S(单位：m)与时间t(单位：s)之间的关系为S(t)=2t³−5t²，则当t=3 s时该质点的瞬时速度为",
        "candidate_methods": [
          "对位移函数求导得到速度函数v(t)=S'(t)，代入t=3计算瞬时速度",
          "使用平均速度逼近法（不推荐，因题目明确要求瞬时速度）"
        ],
        "validation_plan": "验证导数计算是否正确：S'(t)=6t²−10t，代入t=3得v(3)=6×9−10×3=54−30=24 m/s，对应选项B"
      },
      {
        "id": 2,
        "description": "已知航天员选拔时要接受特殊环境的耐受性测试，主要包括前庭功能、超重耐力、失重飞行、飞行跳伞、着陆冲击五项。若这五项测试每天进行一项，连续5天完成，且超重耐力和失重飞行不能安排在相邻两天测试，则选拔测试的安排方案有",
        "candidate_methods": [
          "总排列数减去超重耐力与失重飞行相邻的情况数",
          "先排其他三项，再插空安排超重耐力和失重飞行"
        ],
        "validation_plan": "总排列5!=120；将超重耐力和失重飞行视为一个整体，有4!×2=48种相邻情况；120−48=72，对应选项D"
      },
      {
        "id": 3,
        "description": "已知函数f(x)=e^x−a ln x在区间(0,1)上单调递减，则a的最小值为",
        "candidate_methods": [
          "求导f'(x)=e^x − a/x，令f'(x)≤0在(0,1)恒成立，即a ≥ x e^x，求x e^x在(0,1)的最大值",
          "利用端点极限或函数极值分析"
        ],
        "validation_plan": "f'(x)=e^x − a/x ≤0 ⇒ a ≥ x e^x。令g(x)=x e^x，在(0,1)上g'(x)=e^x + x e^x >0，故g(x)递增，最大值趋近于g(1)=e，所以a≥e，最小值为e，对应选项B"
      },
      {
        "id": 4,
        "description": "若C₂₄^m = C₂₄^(m+2)，则C₃^m + C₄^m + … + C_m^m的值为",
        "candidate_methods": [
          "利用组合数性质C_n^k = C_n^{n−k}，由C₂₄^m = C₂₄^{m+2} 得 m = 24−(m+2) ⇒ 2m=22 ⇒ m=11",
          "然后计算C₃¹¹ + C₄¹¹ + … + C₁₁¹¹，利用组合恒等式∑_{k=r}^n C_k^n = C_{n+1}^{r+1} − C_r^{r+1} 或直接累加"
        ],
        "validation_plan": "由C₂₄^m = C₂₄^{m+2}，根据对称性，m + (m+2) = 24 ⇒ 2m=22 ⇒ m=11。通过组合恒等式计算得C₃¹¹ + C₄¹¹ + … + C₁₁¹¹ = 219，对应选项D"
      }
    ]
  },
  "status": "completed",
  "all_correct": true,
  "overall_comment": "学生在导数应用、排列组合、函数单调性及组合数性质方面表现良好，第四题组合数求和过程需注意恒等式应用细节。",
  "knowledge_points": [
    "导数与瞬时速度",
    "排列组合中的不相邻问题",
    "函数单调性与导数",
    "组合数性质与恒等式"
  ],
  "weakness_clues": [
    "第四题组合数求和的恒等式应用需加强理解"
  ],
  "questions": [
    {
      "id": 1,
      "is_correct": true,
      "final_answer": "B",
      "solution": "对S(t)=2t³−5t²求导得v(t)=6t²−10t，代入t=3得v(3)=54−30=24 m/s",
      "student_feedback": "学生正确应用导数求瞬时速度，方法选择恰当。",
      "analysis": "题目考察导数在物理中的应用，学生掌握良好。",
      "user_markdown": "### 问题1\n**题目**：某质点沿直线运动...\n**答案**：B\n**解析**：对位移函数求导..."
    },
    {
      "id": 2,
      "is_correct": true,
      "final_answer": "D",
      "solution": "总排列5!=120，相邻情况4!×2=48，120−48=72",
      "student_feedback": "学生正确使用捆绑法与插空法解决排列问题。",
      "analysis": "排列组合中不相邻问题的解法掌握到位。",
      "user_markdown": "### 问题2\n**题目**：航天员选拔测试安排...\n**答案**：D\n**解析**：总排列减去相邻情况..."
    },
    {
      "id": 3,
      "is_correct": true,
      "final_answer": "B",
      "solution": "f'(x)=e^x − a/x ≤0 ⇒ a ≥ x e^x，g(x)=x e^x在(0,1)最大值为e",
      "student_feedback": "学生正确分析函数单调性条件，求解过程严谨。",
      "analysis": "函数单调性与导数关系应用准确。",
      "user_markdown": "### 问题3\n**题目**：函数f(x)=e^x−a ln x...\n**答案**：B\n**解析**：通过导数分析单调性..."
    },
    {
      "id": 4,
      "is_correct": true,
      "final_answer": "D",
      "solution": "由C(24,m)=C(24,m+2)得m=11，组合恒等式计算和为219",
      "student_feedback": "学生正确应用组合数对称性，但求和过程需注意恒等式细节。",
      "analysis": "组合数性质掌握良好，恒等式应用需进一步巩固。",
      "user_markdown": "### 问题4\n**题目**：若C₂₄^m = C₂₄^(m+2)...\n**答案**：D\n**解析**：利用组合恒等式计算..."
    }
  ],
  "user_markdown": "学生在导数应用、排列组合、函数单调性及组合数性质方面表现良好，第四题组合数求和过程需注意恒等式应用细节。\n\n?1??\n???B\n???对S(t)=2t³−5t²求导得v(t)=6t²−10t，代入t=3得v(3)=54−30=24 m/s\n???学生正确应用导数求瞬时速度，方法选择恰当。\n\n?2??\n???D\n???总排列5!=120，相邻情况4!×2=48，120−48=72\n???学生正确使用捆绑法与插空法解决排列问题。\n\n?3??\n???B\n???f'(x)=e^x − a/x ≤0 ⇒ a ≥ x e^x，g(x)=x e^x在(0,1)最大值为e\n???学生正确分析函数单调性条件，求解过程严谨。\n\n?4??\n???D\n???由C(24,m)=C(24,m+2)得m=11，组合恒等式计算和为219\n???学生正确应用组合数对称性，但求和过程需注意恒等式细节。\n\n??????导数与瞬时速度?排列组合中的不相邻问题?函数单调性与导数?组合数性质与恒等式\n\n?????????第四题组合数求和的恒等式应用需加强理解",
  "verification_summary": {
    "status": "completed",
    "all_correct": true,
    "knowledge_points": [
      "导数与瞬时速度",
      "排列组合中的不相邻问题",
      "函数单调性与导数",
      "组合数性质与恒等式"
    ],
    "weakness_clues": [
      "第四题组合数求和的恒等式应用需加强理解"
    ],
    "error_points": []
  }
}